request_id_django_log/__init__.py
request_id_django_log/apps.py
request_id_django_log/filters.py
request_id_django_log/middleware.py
request_id_django_log/request_id.py
request_id_django_log/settings.py
tests/__init__.py
tests/settings.py
tests/test_middleware.py
tests/tests_unit.py
tests/urls.py
tests/views.py
request_id_django_log-0.2.0.dist-info/METADATA
request_id_django_log-0.2.0.dist-info/WHEEL
request_id_django_log-0.2.0.dist-info/top_level.txt
request_id_django_log-0.2.0.dist-info/RECORD
